setup.py
minesweeper/__about__.py
minesweeper/__init__.py
minesweeper/gui.py
minesweeper/msboard.py
minesweeper/msgame.py
minesweeper.egg-info/PKG-INFO
minesweeper.egg-info/SOURCES.txt
minesweeper.egg-info/dependency_links.txt
minesweeper.egg-info/pbr.json
minesweeper.egg-info/top_level.txt
minesweeper/imgs/blue_circle.png
minesweeper/imgs/blue_diamond.png
minesweeper/imgs/bomb.png
minesweeper/imgs/boom.png
minesweeper/imgs/continue.png
minesweeper/imgs/eight.png
minesweeper/imgs/five.png
minesweeper/imgs/flag.png
minesweeper/imgs/four.png
minesweeper/imgs/lose.png
minesweeper/imgs/one.png
minesweeper/imgs/question.png
minesweeper/imgs/screen_shot.png
minesweeper/imgs/seven.png
minesweeper/imgs/six.png
minesweeper/imgs/three.png
minesweeper/imgs/two.png
minesweeper/imgs/win.png
minesweeper/imgs/zero.png
scripts/ms-gui.py