Metadata-Version: 1.1
Name: minesweeper
Version: 0.1.4
Summary: A python Minesweeper with interfaces for                  Reinforcement Learning.
Home-page: https://github.com/duguyue100/minesweeper
Author: Yuhuang Hu
Author-email: duguyue100@gmail.com
License: UNKNOWN
Download-URL: https://github.com/duguyue100/minesweeper/tarball/0.1.4
Platform: UNKNOWN
Classifier: Development Status :: 3 - Alpha
Classifier: Intended Audience :: Science/Research
Classifier: Natural Language :: English
Classifier: Operating System :: OS Independent
Classifier: Programming Language :: Python :: 2.7
Classifier: Programming Language :: Python :: 3.5
Classifier: Topic :: Utilities
Classifier: Topic :: Scientific/Engineering
Classifier: Topic :: Scientific/Engineering :: Artificial Intelligence
Classifier: Topic :: Scientific/Engineering :: Visualization
Classifier: Topic :: Software Development :: Libraries :: Python Modules
Classifier: License :: OSI Approved :: MIT License
